<?xml version="1.0" encoding="utf-8"?>
<search>
  
  
  
  <entry>
    <title>使用hexo搭建个人博客</title>
    <link href="/2021/08/21/%E4%B8%AA%E4%BA%BA%E5%8D%9A%E5%AE%A2%E7%BD%91%E7%AB%99%E6%90%AD%E5%BB%BA/"/>
    <url>/2021/08/21/%E4%B8%AA%E4%BA%BA%E5%8D%9A%E5%AE%A2%E7%BD%91%E7%AB%99%E6%90%AD%E5%BB%BA/</url>
    
    <content type="html"><![CDATA[<p>今天看高数积分头有点大，学不进去了，摸了一天鱼，有了这篇博客</p><h3 id="个人博客实现方案"><a href="#个人博客实现方案" class="headerlink" title="个人博客实现方案"></a>个人博客实现方案</h3><p>博客搭建在github上，这样无需购买服务器、买域名、备案、搭建服务器环境、维护等一系列繁琐<del>（费钱）</del>操作，只需新建一个github仓库，在该仓库github page对应的分支添加静态网页的源码，即可外部访问。</p><p>还需要一个博客框架，这样可以只专注博客内容，无需深入了解前端也可以做出精美的博客，hexo是一个比较好用的博客框架，放心，都是免费的。<a href="https://hexo.io/docs/writing.html">https://hexo.io/docs/writing.html</a>)</p><p>主要参考博客：</p><p><a href="https://blog.csdn.net/sinat_37781304/article/details/82729029">https://blog.csdn.net/sinat_37781304/article/details/82729029</a></p><p><a href="https://blog.csdn.net/weixin_43482279/article/details/106894188">https://blog.csdn.net/weixin_43482279/article/details/106894188</a></p><p><a href="https://blog.csdn.net/liuyongshun2/article/details/54629087">https://blog.csdn.net/liuyongshun2/article/details/54629087</a></p><h3 id="创建GitHub仓库"><a href="#创建GitHub仓库" class="headerlink" title="创建GitHub仓库"></a>创建GitHub仓库</h3><p>为博客提供载体，<a href="https://github.com/doee-hc/doee-hc.GitHub.io">https://github.com/doee-hc/doee-hc.GitHub.io</a></p><h3 id="安装Git"><a href="#安装Git" class="headerlink" title="安装Git"></a>安装Git</h3><p>需要通过git将本地的博客文件更新至github的仓库中，git的命令需要在类unix内核下运行，因此可以在linux终端中直接运行，而在windows中常用git bash（一款模拟unix的命令行软件）来操作，安装git自动安装git bash</p><p>git的官网比较慢，可以用阿里的镜像源：<a href="https://npm.taobao.org/mirrors/git-for-windows/">https://npm.taobao.org/mirrors/git-for-windows/</a></p><p>安装完成后，可以参考<a href="https://blog.csdn.net/qq_36667170/article/details/79085301?ops_request_misc=%257B%2522request%255Fid%2522%253A%2522162947855716780264025286%2522%252C%2522scm%2522%253A%252220140713.130102334.pc%255Fblog.%2522%257D&amp;request_id=162947855716780264025286&amp;biz_id=0&amp;utm_medium=distribute.pc_search_result.none-task-blog-2~blog~first_rank_v2~rank_v29-1-79085301.pc_v2_rank_blog_default&amp;utm_term=git&amp;spm=1018.2226.3001.4450">https://blog.csdn.net/qq_36667170/article/details/79085301?ops_request_misc=%257B%2522request%255Fid%2522%253A%2522162947855716780264025286%2522%252C%2522scm%2522%253A%252220140713.130102334.pc%255Fblog.%2522%257D&amp;request_id=162947855716780264025286&amp;biz_id=0&amp;utm_medium=distribute.pc_search_result.none-task-blog-2~blog~first_rank_v2~rank_v29-1-79085301.pc_v2_rank_blog_default&amp;utm_term=git&amp;spm=1018.2226.3001.4450</a></p><p>熟悉git bash的使用，并配置好连接github仓库的 ssh</p><h3 id="安装nodejs"><a href="#安装nodejs" class="headerlink" title="安装nodejs"></a>安装nodejs</h3><p>选择LTS版本安装：</p><p><a href="https://link.csdn.net/?target=https://nodejs.org/en/download/">https://link.csdn.net/?target=https%3A%2F%2Fnodejs.org%2Fen%2Fdownload%2F</a></p><p>注意安装过程中，有一个”Automatically install the necessary toolsxxx“，不要选，否则需要安装一大堆…（它把我的python给更新了，导致很多东西用不了）</p><p>安装完后使用以下命令检查版本（在cmd或者git bash中都行）</p><figure class="highlight bash"><table><tr><td class="gutter"><div class="code-wrapper"><pre><span class="line">1</span><br><span class="line">2</span><br></pre></div></td><td class="code"><pre><code class="hljs bash">node -v<br>npm -v<br></code></pre></td></tr></table></figure><p>如果检查不到，去手动添加一下环境变量</p><h3 id="安装、运行hexo"><a href="#安装、运行hexo" class="headerlink" title="安装、运行hexo"></a>安装、运行hexo</h3><p>参考博客：<a href="https://blog.csdn.net/sinat_37781304/article/details/82729029">https://blog.csdn.net/sinat_37781304/article/details/82729029</a></p><p>进行到这一步时</p><figure class="highlight bash"><table><tr><td class="gutter"><pre><span class="line">1</span><br><span class="line">2</span><br></pre></td><td class="code"><pre><code class="hljs bash"><span class="hljs-built_in">cd</span> myblog //进入这个myblog文件夹<br>npm install<br></code></pre></td></tr></table></figure><p>会出现报错，参考<a href="https://blog.csdn.net/weixin_43482279/article/details/106894188">https://blog.csdn.net/weixin_43482279/article/details/106894188</a> 解决</p><p>按照参考博客操作即可，直到能通过本地服务器正常访问博客</p><p>当使用<code>hexo d</code>时，会出现问题，先根据这篇博客检错：参考<a href="https://blog.csdn.net/liuyongshun2/article/details/54629087">https://blog.csdn.net/liuyongshun2/article/details/54629087</a></p><p>除上面链接里出现的问题，我还遇到一个报错，错误是无法连接到github</p><p>问题应该出在下面的repo</p><figure class="highlight bash"><table><tr><td class="gutter"><pre><span class="line">1</span><br><span class="line">2</span><br><span class="line">3</span><br><span class="line">4</span><br></pre></td><td class="code"><pre><code class="hljs bash">deploy:<br>  <span class="hljs-built_in">type</span>: git<br>  repo: https://github.com/YourgithubName/YourgithubName.github.io.git<br>  branch: master<br></code></pre></td></tr></table></figure><p>这里使用的是https访问，改为ssh访问后问题解决，并且我的github page所关联的分支是gh-pages而不是master，所以要改成gh-pages才生效</p><figure class="highlight bash"><table><tr><td class="gutter"><pre><span class="line">1</span><br><span class="line">2</span><br><span class="line">3</span><br><span class="line">4</span><br></pre></td><td class="code"><pre><code class="hljs bash">deploy:<br>  <span class="hljs-built_in">type</span>: git<br>  repo: git@github.com:YourgithubName/YourgithubName.GitHub.io.git<br>  branch: gh-pages<br></code></pre></td></tr></table></figure><p>注意这里的YourgithubName是自己的github名字</p><h3 id="配置主题"><a href="#配置主题" class="headerlink" title="配置主题"></a>配置主题</h3><p>这部分参照：<a href="https://blog.csdn.net/weixin_43482279/article/details/106894188">https://blog.csdn.net/weixin_43482279/article/details/106894188</a></p><p>我使用的是fluid主题，国人开发和维护，有中文的配置手册，比较方便：<a href="https://github.com/fluid-dev/hexo-theme-fluid">https://github.com/fluid-dev/hexo-theme-fluid</a></p><p>在myblog目录下运行如下命令，克隆fluid主题</p><figure class="highlight bash"><table><tr><td class="gutter"><pre><span class="line">1</span><br></pre></td><td class="code"><pre><code class="hljs bash">git <span class="hljs-built_in">clone</span> https://github.com/fluid-dev/hexo-theme-fluid.git themes/fluid<br></code></pre></td></tr></table></figure><p>按照fluid的配置指南修改博客内容：<a href="https://hexo.fluid-dev.com/docs/guide/">https://hexo.fluid-dev.com/docs/guide/</a></p><h3 id="添加评论功能"><a href="#添加评论功能" class="headerlink" title="添加评论功能"></a>添加评论功能</h3><p>评论功能使用的是valine，在fluid的配置指南中有关于valine设置的简单介绍，具体配置见valine的手册：<a href="https://valine.js.org/configuration.html#appId">https://valine.js.org/configuration.html#appId</a></p><p>需要先注册leancloud、实名认证，不过都是免费的。</p><h3 id="逐步完善"><a href="#逐步完善" class="headerlink" title="逐步完善"></a>逐步完善</h3><p>发布、修改博客</p>]]></content>
    
    
    
  </entry>
  
  
  
  <entry>
    <title>一份本科竞赛总结——电子、自动化方向</title>
    <link href="/2021/03/22/%E4%B8%80%E4%BB%BD%E6%9C%AC%E7%A7%91%E7%AB%9E%E8%B5%9B%E6%80%BB%E7%BB%93%E2%80%94%E2%80%94%E7%94%B5%E5%AD%90%E3%80%81%E8%87%AA%E5%8A%A8%E5%8C%96%E6%96%B9%E5%90%91/"/>
    <url>/2021/03/22/%E4%B8%80%E4%BB%BD%E6%9C%AC%E7%A7%91%E7%AB%9E%E8%B5%9B%E6%80%BB%E7%BB%93%E2%80%94%E2%80%94%E7%94%B5%E5%AD%90%E3%80%81%E8%87%AA%E5%8A%A8%E5%8C%96%E6%96%B9%E5%90%91/</url>
    
    <content type="html"><![CDATA[<h2 id="前言"><a href="#前言" class="headerlink" title="前言"></a>前言</h2><p>一篇流水账，给这两年半的经历画上句号。</p><h2 id="大一上学期："><a href="#大一上学期：" class="headerlink" title="大一上学期："></a>大一上学期：</h2><p>  刷了一遍<a href="https://www.bilibili.com/video/BV19W411B7w1?from=search&seid=13492696000186458664">浙大翁凯的C语言网课</a></p><p>  学会用proteus做单片机仿真</p><p>  学习51单片机和一些常用的外设</p><p>  用单片机制作了一些小作品：贪吃蛇、五子棋等等</p><p>  开始写博客</p><p>  学会简单的焊接<br>  <img src="https://img-blog.csdnimg.cn/20210321205701797.gif#pic_center" alt="在这里插入图片描述"></p><h2 id="大一下学期"><a href="#大一下学期" class="headerlink" title="大一下学期"></a>大一下学期</h2><p>  参加了本科的第一个比赛——Robomaster校赛，获得冠军，拿到了来自DJI的奖金😄，后加入校Robomaster战队<br>  <img src="https://img-blog.csdnimg.cn/20210321210541639.gif#pic_center" alt="在这里插入图片描述"></p><p>学习stm32，复现了几道电赛题目，19年电赛惜败<br><a href="https://blog.csdn.net/weixin_44578655/article/details/99649173?spm=1001.2014.3001.5501">2019全国大学生电子设计竞赛备赛笔记–风力摆–板球–模拟曲射电磁炮</a></p><h2 id="大二上学期"><a href="#大二上学期" class="headerlink" title="大二上学期"></a>大二上学期</h2><p>学习简单的双层PCB绘制以及恶补硬件知识<br>参加灭火机器人的比赛（这个小东西好像是当年省里最快的成绩）<br><img src="https://img-blog.csdnimg.cn/20210321220645341.gif#pic_center" alt="在这里插入图片描述"><br>参加山东省科技创新大赛，第一次参加这类<del>ppt</del>大赛，工作量不大，但作品包装的不错，拿到了二等奖。</p><p>接下来都是在RM队伍的工作：<br>绘制机器人主控板</p><p>接触数字电源（同步整流BUCK拓扑），制作机器人的恒功率电源管理，没有深入下去，不过电源是个很好的方向。</p><p>学习上位机，做了一款串口示波器上位机，原意是想用到机器人日常调试中的，取名RM DEBUGGER，因为比赛时间太赶，最终它永久躺在文件夹里。<img src="https://img-blog.csdnimg.cn/20210321212311477.gif" alt="在这里插入图片描述"><img src="https://img-blog.csdnimg.cn/20210321212311461.gif" alt="在这里插入图片描述"><br><img src="https://img-blog.csdnimg.cn/20210321212311422.gif" alt="在这里插入图片描述"><br><img src="https://img-blog.csdnimg.cn/20210321212311338.gif" alt="在这里插入图片描述"></p><h2 id="大二下学期（疫情在家）"><a href="#大二下学期（疫情在家）" class="headerlink" title="大二下学期（疫情在家）"></a>大二下学期（疫情在家）</h2><p>开始接触NRF52系列蓝牙SOC，入坑了很久的机械键盘，很想自己做一个，最终烂尾，做的比买的还贵。<br>做了一款DAPlink，很好用，伴随整个假期。<br><img src="https://img-blog.csdnimg.cn/20210322082028650.jpg?x-oss-process=image/watermark,type_ZmFuZ3poZW5naGVpdGk,shadow_10,text_aHR0cHM6Ly9ibG9nLmNzZG4ubmV0L3dlaXhpbl80NDU3ODY1NQ==,size_16,color_FFFFFF,t_70#pic_center" alt="在这里插入图片描述"></p><p>完成大创项目，学习FreeRTOS，做了一个联网储物柜，项目顺利结题。<br><img src="https://img-blog.csdnimg.cn/20210321215007444.gif#pic_center" alt="在这里插入图片描述"><br><a href="https://oshwhub.com/doee/wai-mai-zi-ti-gui-she-bei-duan-z">外卖自提柜设备端开源</a><br><strong>6月份返校</strong><br>实验室的大家应征返校备战Robomaster国赛，因为宿舍又潮又热，我们就住在实验室（空调房）。日常工作就是画板、焊板、调板、炸板、修板。</p><p>国赛拿到了不错的成绩，但没有现场的RM已经没了灵魂，很想去深圳。</p><p>参加了智能车竞赛，比赛时间与Robomsater国赛冲突，国赛答辩完成后，还剩大概不到一周时间，我参加的是直立节能组，到比赛前几天，才勉强解决结构、直立的问题<br><img src="https://img-blog.csdnimg.cn/20210321222727527.gif#pic_center" alt="在这里插入图片描述"><br><img src="https://img-blog.csdnimg.cn/20210321222900274.gif#pic_center" alt="在这里插入图片描述"></p><p><img src="https://img-blog.csdnimg.cn/20210321234747545.jpg?x-oss-process=image/watermark,type_ZmFuZ3poZW5naGVpdGk,shadow_10,text_aHR0cHM6Ly9ibG9nLmNzZG4ubmV0L3dlaXhpbl80NDU3ODY1NQ==,size_16,color_FFFFFF,t_70#pic_center" alt="在这里插入图片描述"></p><p>赛前48小时爆肝</p><p><img src="https://img-blog.csdnimg.cn/20210321232438428.gif#pic_center" alt="在这里插入图片描述"><br><img src="https://img-blog.csdnimg.cn/20210321232536238.gif#pic_center" alt="在这里插入图片描述"></p><p>从比赛三天前开始下场地调车，在比赛前一天晚上调到上图效果，比赛当天的早上开始解决入库问题，最终只能实现趴地入库。</p><p>现场比赛由于干簧管没识别到磁标致成绩无效，智能车之旅就此结束。</p><p>因为过程过于狼狈，智能车的参赛经历没有记录下来，就在这里多说一点。</p><blockquote><p>关于智能车竞赛，我还是忍不住吐槽，整个比赛就像是逐飞和龙邱以及众多tb小店的圈钱大赛，我全程除了比赛必须的器械之外，从不买他两家的东西，这也是选择自制车模组别的原因。</p></blockquote><h2 id="大三上学期"><a href="#大三上学期" class="headerlink" title="大三上学期"></a>大三上学期</h2><p>招募新队员，做培训，离开RM队伍。</p><p>此前学校一直有竞赛推免的名额，虽然对这种事一直后知后觉，但在实验室结识了一群有想法又优秀的人，受其感染，我也打算拼一拼。</p><p>因为疫情，之前积压的很多比赛，都推到这个学期，这是个几近疯狂的学期。</p><p>1.电子设计大赛省赛：<br><a href="https://blog.csdn.net/weixin_44578655/article/details/109020022">2020年TI杯大学生电子设计大赛 无线运动传感器节点 备赛、参赛实录（历时一个月）</a></p><p>2.全国大学生嵌入式芯片与系统设计竞赛暨智能互联创新大赛（智能互联大赛）<br>电赛在2021年10月15日测评完，这个比赛10月16日就截至提交作品，我使用的是之前做的物联网储物柜，但需要把FreeRTOS改成RT-thread，15日晚把RT-Thread改完，接着准备答辩稿，拍视频+剪辑，卡点提交。<br><a href="https://blog.csdn.net/weixin_44578655/article/details/109700513">RT-Thread学习笔记</a></p><p>3.蓝桥杯省赛：<br>上面的比赛在10月16日傍晚忙完提交后，接着来到10月17日，蓝桥杯省赛，与蓝桥杯省赛同一天的是省电赛的二次答辩，还好电赛答辩拖到了傍晚，蓝桥杯在白天，时间不冲突。蓝桥杯准备不充足，题目差点没做完。</p><p>这三个比赛挤在10天里，差点送走我。</p><p>电赛全程顺利，再加上今年本土作战，参赛体验很好。</p><p>蓝桥杯最终勉强通过，进入国赛，但因为疫情无缘<strong>公款北京两日游</strong></p><p>智能互联大赛只拿到了山东赛区二等奖，南京也没去成</p><p>4.山东省科技创新大赛：<br>文字润色工作，尽力了，未出线。</p><p>5.蓝桥杯国赛：<br>准备充足，题目也比较简单，拿到了期待已久的国一。</p><p>6.另收获几个省奖（山东省xxx大赛）</p><p>在准备电赛的时候，当年的推免文件已经下发，这次统一取消了竞赛推免的名额，改为加分。眼看着已经找好导师的学长，就地买书考研，我也不抱幻想了。</p><p>离开RM后，有很多想了解的方向：<br>机器学习、CV、电源、FPGA、linux…<br>但我花了这最后一个学期炒冷饭，收获了几张不再有用的证书。</p><p><strong>寒假</strong><br>linux 学了一点基本操作</p><p>opencv（python） 一点点</p><p>FPGA：《CPU自制入门》看了一半，能大概看懂Verilog HDL，学会用iverilog+VScode</p><p>电源：计划做一个数控电源+焊台+风枪的工作台，只画了原理图</p><h2 id="大三下学期"><a href="#大三下学期" class="headerlink" title="大三下学期"></a>大三下学期</h2><p>开始考研长跑</p>]]></content>
    
    
    
  </entry>
  
  
  
  
</search>
